{
  "file_name": "input_data/bundles/space/doc_space_planets_basic.json",
  "doc_id": "doc_space_planets_basic",
  "topic": "Các hành tinh",
  "domain": "space",
  "lesson_level": "nhan_biet",
  "age": 8,
  "source": {
    "title": "Planets for Kids",
    "url": "https://example.com/planets_basic",
    "publisher": "EduScience",
    "retrieved_at": "2026-04-07",
    "confidence": 0.94
  },
  "text": "Các hành tinh là những thiên thể quay quanh Mặt Trời. Trong Hệ Mặt Trời có 8 hành tinh như Trái Đất, Sao Hỏa và Sao Mộc. Các hành tinh không tự phát ra ánh sáng mà nhận ánh sáng từ Mặt Trời. Mỗi hành tinh có kích thước và đặc điểm khác nhau.",
  "concepts": [
    {
      "id": "c_planet",
      "name": "Hành tinh",
      "description": "Thiên thể quay quanh Mặt Trời.",
      "difficulty": 1,
      "parent_id": null
    },
    {
      "id": "c_sun",
      "name": "Mặt Trời",
      "description": "Ngôi sao trung tâm của Hệ Mặt Trời.",
      "difficulty": 1,
      "parent_id": null
    },
    {
      "id": "c_solar_system",
      "name": "Hệ Mặt Trời",
      "description": "Hệ gồm Mặt Trời và các hành tinh.",
      "difficulty": 1,
      "parent_id": null
    },
    {
      "id": "c_earth",
      "name": "Trái Đất",
      "description": "Một hành tinh có sự sống.",
      "difficulty": 1,
      "parent_id": "c_planet"
    },
    {
      "id": "c_mars",
      "name": "Sao Hỏa",
      "description": "Hành tinh đỏ.",
      "difficulty": 2,
      "parent_id": "c_planet"
    },
    {
      "id": "c_jupiter",
      "name": "Sao Mộc",
      "description": "Hành tinh lớn nhất.",
      "difficulty": 2,
      "parent_id": "c_planet"
    },
    {
      "id": "c_light",
      "name": "Ánh sáng",
      "description": "Ánh sáng từ Mặt Trời chiếu đến hành tinh.",
      "difficulty": 1,
      "parent_id": null
    },
    {
      "id": "c_orbit",
      "name": "Quỹ đạo",
      "description": "Đường đi của hành tinh quanh Mặt Trời.",
      "difficulty": 2,
      "parent_id": null
    }
  ],
  "relations": [
    {"from_id": "c_planet", "to_id": "c_solar_system", "relation": "PART_OF", "weight": 0.95},
    {"from_id": "c_planet", "to_id": "c_sun", "relation": "RELATED_TO", "weight": 0.9},
    {"from_id": "c_planet", "to_id": "c_orbit", "relation": "HAS", "weight": 0.9},

    {"from_id": "c_earth", "to_id": "c_planet", "relation": "IS_A", "weight": 0.95},
    {"from_id": "c_mars", "to_id": "c_planet", "relation": "IS_A", "weight": 0.95},
    {"from_id": "c_jupiter", "to_id": "c_planet", "relation": "IS_A", "weight": 0.95},

    {"from_id": "c_planet", "to_id": "c_light", "relation": "HAS", "weight": 0.8},
    {"from_id": "c_light", "to_id": "c_sun", "relation": "CAUSES", "weight": 0.9},

    {"from_id": "c_solar_system", "to_id": "c_sun", "relation": "HAS", "weight": 0.95},

    {"from_id": "c_planet", "to_id": "c_earth", "relation": "HAS", "weight": 0.7},
    {"from_id": "c_planet", "to_id": "c_mars", "relation": "HAS", "weight": 0.7},
    {"from_id": "c_planet", "to_id": "c_jupiter", "relation": "HAS", "weight": 0.7},

    {"from_id": "c_orbit", "to_id": "c_sun", "relation": "RELATED_TO", "weight": 0.8},

    {"from_id": "c_earth", "to_id": "c_planet", "relation": "EXAMPLE_OF", "weight": 0.7},
    {"from_id": "c_mars", "to_id": "c_planet", "relation": "EXAMPLE_OF", "weight": 0.7},
    {"from_id": "c_jupiter", "to_id": "c_planet", "relation": "EXAMPLE_OF", "weight": 0.7},

    {"from_id": "c_planet", "to_id": "c_sun", "relation": "CAUSES", "weight": 0.6},

    {"from_id": "c_sun", "to_id": "c_light", "relation": "HAS", "weight": 0.9}
  ],
  "qa_bank": [
    {"id": "qa_1", "concept_id": "c_planet", "question": "Hành tinh là gì?", "answer": "Thiên thể quay quanh Mặt Trời", "type": "open", "options": [], "difficulty": 1},
    {"id": "qa_2", "concept_id": "c_planet", "question": "Hành tinh có tự phát ra ánh sáng không?", "answer": "Không", "type": "yesno", "options": [], "difficulty": 1},

    {"id": "qa_3", "concept_id": "c_sun", "question": "Mặt Trời là gì?", "answer": "Ngôi sao trung tâm", "type": "open", "options": [], "difficulty": 1},
    {"id": "qa_4", "concept_id": "c_sun", "question": "Mặt Trời có phát ra ánh sáng không?", "answer": "Có", "type": "yesno", "options": [], "difficulty": 1},

    {"id": "qa_5", "concept_id": "c_solar_system", "question": "Hệ Mặt Trời gồm những gì?", "answer": "Mặt Trời và các hành tinh", "type": "open", "options": [], "difficulty": 1},
    {"id": "qa_6", "concept_id": "c_solar_system", "question": "Hệ Mặt Trời có chứa hành tinh không?", "answer": "Có", "type": "yesno", "options": [], "difficulty": 1},

    {"id": "qa_7", "concept_id": "c_earth", "question": "Trái Đất là gì?", "answer": "Một hành tinh", "type": "open", "options": [], "difficulty": 1},
    {"id": "qa_8", "concept_id": "c_earth", "question": "Trái Đất có sự sống không?", "answer": "Có", "type": "yesno", "options": [], "difficulty": 1},

    {"id": "qa_9", "concept_id": "c_mars", "question": "Sao Hỏa có màu gì?", "answer": "Màu đỏ", "type": "open", "options": [], "difficulty": 1},
    {"id": "qa_10", "concept_id": "c_mars", "question": "Sao Hỏa có phải là hành tinh không?", "answer": "Có", "type": "yesno", "options": [], "difficulty": 1},

    {"id": "qa_11", "concept_id": "c_jupiter", "question": "Sao Mộc là hành tinh như thế nào?", "answer": "Lớn nhất", "type": "open", "options": [], "difficulty": 1},
    {"id": "qa_12", "concept_id": "c_jupiter", "question": "Sao Mộc có phải là hành tinh không?", "answer": "Có", "type": "yesno", "options": [], "difficulty": 1},

    {"id": "qa_13", "concept_id": "c_light", "question": "Ánh sáng của hành tinh đến từ đâu?", "answer": "Mặt Trời", "type": "open", "options": [], "difficulty": 1},
    {"id": "qa_14", "concept_id": "c_light", "question": "Hành tinh có tự tạo ra ánh sáng không?", "answer": "Không", "type": "yesno", "options": [], "difficulty": 1},

    {"id": "qa_15", "concept_id": "c_orbit", "question": "Quỹ đạo là gì?", "answer": "Đường đi quanh Mặt Trời", "type": "open", "options": [], "difficulty": 2},
    {"id": "qa_16", "concept_id": "c_orbit", "question": "Hành tinh có quay quanh Mặt Trời không?", "answer": "Có", "type": "yesno", "options": [], "difficulty": 1},

    {"id": "qa_17", "concept_id": "c_planet", "question": "Có bao nhiêu hành tinh trong Hệ Mặt Trời?", "answer": "8", "type": "open", "options": [], "difficulty": 1},
    {"id": "qa_18", "concept_id": "c_planet", "question": "Điền từ: Hành tinh quay quanh ____.", "answer": "Mặt Trời", "type": "fill", "options": [], "difficulty": 1}
  ]
}